bindpy/__init__.py
bindpy/bind.py
bindpy/placeholder.py
LICENSE
bindpy-0.1.1.dist-info/LICENSE
bindpy-0.1.1.dist-info/METADATA
bindpy-0.1.1.dist-info/WHEEL
bindpy-0.1.1.dist-info/RECORD
