Metadata-Version: 2.1
Name: bindpy
Version: 0.1.1
Summary: The bindpy package allows for partial application of arguments to a function, making it easy to create specialized versions of the function with some arguments pre-filled.
Home-page: https://github.com/avdosev/bindpy
License: MIT
Keywords: bind,bindpy,bind_front,bind_back,partial,functools
Author: Nikita Avdosev
Requires-Python: >=3.0
Classifier: License :: OSI Approved :: MIT License
Classifier: Programming Language :: Python :: 3
Classifier: Programming Language :: Python :: 3.4
Classifier: Programming Language :: Python :: 3.5
Classifier: Programming Language :: Python :: 3.6
Classifier: Programming Language :: Python :: 3.7
Classifier: Programming Language :: Python :: 3.8
Classifier: Programming Language :: Python :: 3.9
Classifier: Programming Language :: Python :: 3.10
Classifier: Programming Language :: Python :: 3.11
Project-URL: Repository, https://github.com/avdosev/bindpy
